Metadata-Version: 2.4
Name: brother_ql_next
Version: 0.11.4
Summary: Python package to talk to Brother QL label printers
Author-email: Philipp Klaus <philipp.l.klaus@web.de>, LunarEclipse <luna@lunareclipse.zone>
Maintainer-email: LunarEclipse <luna@lunareclipse.zone>
License: GPL-3.0-only
Project-URL: repository, https://github.com/LunarEclipse363/brother_ql_next
Project-URL: changelog, https://github.com/LunarEclipse363/brother_ql_next/blob/main/CHANGELOG.md
Keywords: Brother,Label,Printer,QL-500,QL-550,QL-560,QL-570,QL-600,QL-700,QL-710W,QL-720NW,QL-800,QL-810W,QL-820NWB,QL-1050,QL-1060N,QL-1100,QL-1100NWB,QL-1115NWB
Classifier: Development Status :: 4 - Beta
Classifier: Operating System :: OS Independent
Classifier: License :: OSI Approved :: GNU General Public License v3 (GPLv3)
Classifier: Programming Language :: Python
Classifier: Programming Language :: Python :: 3
Classifier: Topic :: Scientific/Engineering :: Visualization
Classifier: Topic :: System :: Hardware :: Hardware Drivers
Requires-Python: >=3.9
License-File: LICENSE
Requires-Dist: click
Requires-Dist: future
Requires-Dist: packbits
Requires-Dist: pillow>=3.3.0
Requires-Dist: pyusb
Requires-Dist: attrs
Requires-Dist: typing; python_version < "3.5"
Requires-Dist: enum34; python_version < "3.4"
Requires-Dist: jsons
Dynamic: license-file
